pyldapsearch/__init__.py
pyldapsearch/__main__.py
pyldapsearch-0.1.9.dist-info/LICENSE
pyldapsearch-0.1.9.dist-info/METADATA
pyldapsearch-0.1.9.dist-info/WHEEL
pyldapsearch-0.1.9.dist-info/entry_points.txt
pyldapsearch-0.1.9.dist-info/RECORD
