Metadata-Version: 2.3
Name: pyldapsearch
Version: 0.1.9
Summary: Tool for issuing manual LDAP queries which offers bofhound compatible output
Author: Matt Creel
Requires-Python: >=3.9,<4.0
Classifier: Programming Language :: Python :: 3
Classifier: Programming Language :: Python :: 3.9
Classifier: Programming Language :: Python :: 3.10
Classifier: Programming Language :: Python :: 3.11
Classifier: Programming Language :: Python :: 3.12
Classifier: Programming Language :: Python :: 3.13
Requires-Dist: cffi (>=1.17.1,<2.0.0)
Requires-Dist: click (==8.1.8)
Requires-Dist: impacket (>=0.10.0,<0.11.0)
Requires-Dist: ldap3-bleeding-edge (>=2.10.1.1338,<3.0.0.0)
Requires-Dist: pyasn1 (>=0.4.8,<0.5.0)
Requires-Dist: pycryptodome (>=3.20.0,<4.0.0)
Requires-Dist: rich (>=12.5.1,<13.0.0)
Requires-Dist: setuptools (>=75.8.2,<76.0.0)
Requires-Dist: typer (>=0.9,<0.10)
Project-URL: Homepage, https://github.com/fortalice/pyldapsearch
Project-URL: Repository, https://github.com/fortalice/pyldapsearch
